pzgram/__init__.py
pzgram/api.py
pzgram/bot.py
pzgram/exceptions.py
pzgram/inline.py
pzgram/media_objects.py
pzgram/objects.py
pzgram/parsing.py
pzgram/useful.py
pzgram-1.0.2.dist-info/LICENSE.txt
pzgram-1.0.2.dist-info/METADATA
pzgram-1.0.2.dist-info/WHEEL
pzgram-1.0.2.dist-info/top_level.txt
pzgram-1.0.2.dist-info/RECORD
