Metadata-Version: 2.1
Name: pzgram
Version: 1.0.2
Summary: A pz-way to create your telegram bot
Home-page: https://github.com/infopz/pzgram
Author: Giovani Casari
Author-email: casari.giovanni@gmail.com
License: Apache2
Download-URL: https://github.com/infopz/pzgram/archive/1.0.2.tar.gz
Keywords: telegram,telegram-bot,telegram-api
Platform: UNKNOWN
Requires-Dist: requests (>=2.18.4)
